turbanet/__init__.py
turbanet/loss.py
turbanet/turba_train_state.py
turbanet-0.3.1.dist-info/licenses/LICENSE
turbanet-0.3.1.dist-info/METADATA
turbanet-0.3.1.dist-info/WHEEL
turbanet-0.3.1.dist-info/top_level.txt
turbanet-0.3.1.dist-info/RECORD
